mypckg/Functions.py
mypckg/__init__.py
marvel_case_aaw-0.1.0.dist-info/LICENSE
marvel_case_aaw-0.1.0.dist-info/METADATA
marvel_case_aaw-0.1.0.dist-info/WHEEL
marvel_case_aaw-0.1.0.dist-info/top_level.txt
marvel_case_aaw-0.1.0.dist-info/RECORD
